llm_recorder-0.1.0.dist-info/METADATA
llm_recorder-0.1.0.dist-info/WHEEL
llm_recorder-0.1.0.dist-info/entry_points.txt
llm_recorder-0.1.0.dist-info/licenses/LICENSE
llm_recorder/__init__.py
llm_recorder/llm_injected_proxy.py
llm_recorder/llm_recorder.py
llm_recorder/providers/anthropic_recorder.py
llm_recorder/providers/google_recorder.py
llm_recorder/providers/http_recorder.py
llm_recorder/providers/litellm_recorder.py
llm_recorder/providers/openai_recorder.py
llm_recorder/providers/test_litellm.py
llm_recorder/test_llm_recorder.py
llm_recorder-0.1.0.dist-info/RECORD
