Metadata-Version: 2.1
Name: llm-recorder
Version: 0.1.0
Summary: Record and replay LLM interactions
Author-Email: Your Name <your.email@example.com>
License: MIT
Project-URL: Homepage, https://github.com/zby/llm_recorder
Requires-Python: >=3.9
Requires-Dist: litellm>=1.30.7
Provides-Extra: openai
Requires-Dist: openai>=1.0.0; extra == "openai"
Provides-Extra: anthropic
Requires-Dist: anthropic; extra == "anthropic"
Provides-Extra: google
Requires-Dist: google-generativeai; extra == "google"
